[
  {
    "Name": "Aitor_Tilla"
  },
  {
    "Name": "Elena_Nito"
  },
  {
    "Name": "Lola_Mento"
  },
  {
    "Name": "Dolores_Delano"
  },
  {
    "Name": "Elba_Ginon"
  },
  {
    "Name": "Elvis_Ko"
  },
  {
    "Name": "Helen_Chufe"
  },
  {
    "Name": "Paco_Gerte"
  },
  {
    "Name": "Tommy_Vercetti"
  },
  {
    "Name": "Jorge_Nitales"
  },
  {
    "Name": "Paul_Vazo"
  },
  {
    "Name": "Susana_Torio"
  },
  {
    "Name": "Rosa_Melano"
  },
  {
    "Name": "Larry_Capija"
  },
  {
    "Name": "Benito_Camelo"
  },
  {
    "Name": "Elton_Tito"
  }
]